{
  "version": "0.22.37",
  "entry": "main.js",
  "modules": [
    "main.js",
    "playlists.js",
    "settings.js",
    "store.js"
  ],
  "css": "style.css",
  "html": "index.html",
  "notes": "THE grid fix: YouTube-style cards finally show their covers everywhere (a stray align-items collapsed the thumbnails to zero width), playback starts noticeably faster (the file tail is cached for the format probe), and UI updates now refuse to land on an app that is too old for them.",
  "platforms": [
    "linux",
    "windows",
    "macos",
    "android"
  ],
  "min_native": "0.22.35"
}